test_54545454/__init__.py
test_54545454/api_helper.py
test_54545454/configuration.py
test_54545454/decorators.py
test_54545454/test_54545454_client.py
test_54545454/controllers/__init__.py
test_54545454/controllers/base_controller.py
test_54545454/controllers/simple_calculator_controller.py
test_54545454/exceptions/__init__.py
test_54545454/exceptions/api_exception.py
test_54545454/http/__init__.py
test_54545454/http/http_call_back.py
test_54545454/http/http_client.py
test_54545454/http/http_context.py
test_54545454/http/http_method_enum.py
test_54545454/http/http_request.py
test_54545454/http/http_response.py
test_54545454/http/requests_client.py
test_54545454/models/__init__.py
test_54545454/models/operation_type_enum.py
tests/__init__.py
tests/http_response_catcher.py
tests/test_helper.py
tests/controllers/__init__.py
tests/controllers/controller_test_base.py
tests/controllers/test_simple_calculator_controller.py
test54545454-1.0.0.dist-info/LICENSE
test54545454-1.0.0.dist-info/METADATA
test54545454-1.0.0.dist-info/WHEEL
test54545454-1.0.0.dist-info/top_level.txt
test54545454-1.0.0.dist-info/RECORD
